{
  "generated_at_utc": "2026-03-18T15:44:24.478659+00:00",
  "input": "/workspaces/lca-simu/etudecas/simulation_prep/result/reference_baseline/supply_graph_reference_baseline_current.json",
  "run_script": "/workspaces/lca-simu/etudecas/simulation/run_first_simulation.py",
  "scenario_id": "scn:BASE",
  "days": 365,
  "service_threshold": 0.95,
  "service_soft_threshold": 0.93,
  "backlog_increase_pct": 0.25,
  "cost_increase_pct": 0.1,
  "selected_suppliers": [
    "SDC-1450",
    "SDC-VD0914690A",
    "SDC-VD0525412A",
    "SDC-VD0901566A"
  ],
  "artifact_mode": "compact",
  "kept_detailed_cases": [
    "baseline"
  ],
  "baseline": {
    "case_id": "baseline",
    "parameter_key": "baseline",
    "parameter_group": "baseline",
    "parameter_label": "Baseline",
    "realism_focus": "baseline",
    "level": 1.0,
    "status": "ok",
    "case_input": "/workspaces/lca-simu/etudecas/simulation/sensibility/reference_baseline_threshold_compact/cases/baseline/input_case.json",
    "case_output_dir": "/workspaces/lca-simu/etudecas/simulation/sensibility/reference_baseline_threshold_compact/cases/baseline/simulation_output",
    "kpi::total_demand": 17400.0,
    "kpi::total_served": 16556.7905,
    "kpi::ending_backlog": 843.2095,
    "kpi::fill_rate": 0.95154,
    "kpi::total_shipped": 160731.6544,
    "kpi::total_arrived": 157399.3277,
    "kpi::total_produced": 94445.1496,
    "kpi::avg_inventory": 8253511.0415,
    "kpi::ending_inventory": 8024596.4229,
    "kpi::total_transport_cost": 71615.5618,
    "kpi::total_holding_cost": 19170880.3166,
    "kpi::total_purchase_cost": 13829.9875,
    "kpi::total_logistics_cost": 19242495.8784,
    "kpi::total_cost": 19256325.8659,
    "kpi::total_external_procured_ordered_qty": 0.0,
    "kpi::total_external_procured_arrived_qty": 0.0,
    "kpi::total_external_procured_rejected_qty": 0.0,
    "kpi::total_external_procured_qty": 0.0,
    "kpi::total_external_procurement_cost": 0.0,
    "kpi::total_estimated_source_ordered_qty": 49570.1,
    "kpi::total_estimated_source_replenished_qty": 47944.2243,
    "kpi::total_estimated_source_rejected_qty": 0.0,
    "kpi::total_opening_stock_bootstrap_qty": 8523781.9898,
    "kpi::total_unreliable_loss_qty": 0.0,
    "kpi::total_supplier_capacity_binding_qty": 0.0,
    "kpi::cost_share_holding": 0.995563,
    "kpi::cost_share_transport": 0.003719,
    "kpi::cost_share_purchase": 0.000718
  },
  "deterministic_check": {
    "status": "pass",
    "max_abs_diff": 0.0,
    "abs_diff_by_kpi": {
      "fill_rate": 0.0,
      "ending_backlog": 0.0,
      "total_cost": 0.0,
      "total_external_procured_ordered_qty": 0.0,
      "avg_inventory": 0.0
    }
  },
  "parameter_count": 32,
  "simulation_count": 157,
  "critical_by_service_threshold": [
    {
      "parameter_label": "Bootstrap stock initial",
      "parameter_key": "opening_stock_bootstrap_scale",
      "cross_at": 0.25,
      "safe_band_low": null,
      "safe_band_high": null,
      "max_fill_rate_drop": 0.6201810000000001
    },
    {
      "parameter_label": "Lead time fournisseur SDC-VD0914690A",
      "parameter_key": "supplier_lead_time_node::SDC-VD0914690A",
      "cross_at": 0.7,
      "safe_band_low": 1.0,
      "safe_band_high": 1.5,
      "max_fill_rate_drop": 0.1353660000000001
    },
    {
      "parameter_label": "Capacite M-1430",
      "parameter_key": "capacity_node::M-1430",
      "cross_at": 0.7,
      "safe_band_low": 1.0,
      "safe_band_high": 1.3,
      "max_fill_rate_drop": 0.13366500000000003
    },
    {
      "parameter_label": "Lead time global",
      "parameter_key": "lead_time_scale",
      "cross_at": 0.75,
      "safe_band_low": 1.0,
      "safe_band_high": 1.5,
      "max_fill_rate_drop": 0.10572500000000007
    },
    {
      "parameter_label": "Fiabilite fournisseur globale",
      "parameter_key": "supplier_reliability_scale",
      "cross_at": 0.85,
      "safe_band_low": 1.0,
      "safe_band_high": 1.0,
      "max_fill_rate_drop": 0.262378
    },
    {
      "parameter_label": "Demande 268967",
      "parameter_key": "demand_item::item:268967",
      "cross_at": 1.1,
      "safe_band_low": 0.8,
      "safe_band_high": 1.0,
      "max_fill_rate_drop": 0.08262600000000009
    },
    {
      "parameter_label": "Periode de revue",
      "parameter_key": "review_period_scale",
      "cross_at": 2.0,
      "safe_band_low": 1.0,
      "safe_band_high": 1.0,
      "max_fill_rate_drop": 0.46760700000000005
    }
  ],
  "strongest_fill_effects": [
    {
      "parameter_key": "opening_stock_bootstrap_scale",
      "parameter_group": "global",
      "parameter_label": "Bootstrap stock initial",
      "realism_focus": "model_protection",
      "levels": [
        0.25,
        0.5,
        0.75,
        1.0,
        1.25
      ],
      "baseline_fill_rate": 0.95154,
      "baseline_backlog": 843.2095,
      "baseline_total_cost": 19256325.8659,
      "baseline_external_procured_qty": 0.0,
      "baseline_avg_inventory": 8253511.0415,
      "fill_rate_monotonicity": "increasing",
      "ending_backlog_monotonicity": "decreasing",
      "total_cost_monotonicity": "increasing",
      "max_fill_rate_drop": 0.6201810000000001,
      "max_backlog_increase": 10791.144499999999,
      "max_total_cost_increase": -7210137.3632,
      "fill_rate_cross_service_threshold_at": 0.25,
      "fill_rate_cross_soft_threshold_at": 0.25,
      "ending_backlog_cross_threshold_at": 0.25,
      "total_cost_cross_threshold_at": null,
      "safe_band_low": null,
      "safe_band_high": null,
      "steepest_fill_segment": [
        0.25,
        0.5
      ],
      "fill_rate_min": 0.331359,
      "fill_rate_max": 0.784757,
      "ending_backlog_min": 3745.2266,
      "ending_backlog_max": 11634.354,
      "total_cost_min": 2719922.0366,
      "total_cost_max": 12046188.5027,
      "external_procured_qty_min": 0.0,
      "external_procured_qty_max": 0.0,
      "avg_inventory_min": 1030979.3977,
      "avg_inventory_max": 5104927.8259
    },
    {
      "parameter_key": "review_period_scale",
      "parameter_group": "global",
      "parameter_label": "Periode de revue",
      "realism_focus": "planning_policy",
      "levels": [
        1.0,
        2.0,
        3.0,
        5.0,
        7.0
      ],
      "baseline_fill_rate": 0.95154,
      "baseline_backlog": 843.2095,
      "baseline_total_cost": 19256325.8659,
      "baseline_external_procured_qty": 0.0,
      "baseline_avg_inventory": 8253511.0415,
      "fill_rate_monotonicity": "decreasing",
      "ending_backlog_monotonicity": "increasing",
      "total_cost_monotonicity": "increasing",
      "max_fill_rate_drop": 0.46760700000000005,
      "max_backlog_increase": 8136.3581,
      "max_total_cost_increase": 506206.39169999957,
      "fill_rate_cross_service_threshold_at": 2.0,
      "fill_rate_cross_soft_threshold_at": 2.0,
      "ending_backlog_cross_threshold_at": 2.0,
      "total_cost_cross_threshold_at": null,
      "safe_band_low": 1.0,
      "safe_band_high": 1.0,
      "steepest_fill_segment": [
        2.0,
        3.0
      ],
      "fill_rate_min": 0.483933,
      "fill_rate_max": 0.95154,
      "ending_backlog_min": 843.2095,
      "ending_backlog_max": 8979.5676,
      "total_cost_min": 19256325.8659,
      "total_cost_max": 19762532.2576,
      "external_procured_qty_min": 0.0,
      "external_procured_qty_max": 0.0,
      "avg_inventory_min": 8253511.0415,
      "avg_inventory_max": 8708616.9734
    },
    {
      "parameter_key": "supplier_reliability_scale",
      "parameter_group": "global",
      "parameter_label": "Fiabilite fournisseur globale",
      "realism_focus": "exogenous_network",
      "levels": [
        0.85,
        0.9,
        0.95,
        1.0
      ],
      "baseline_fill_rate": 0.95154,
      "baseline_backlog": 843.2095,
      "baseline_total_cost": 19256325.8659,
      "baseline_external_procured_qty": 0.0,
      "baseline_avg_inventory": 8253511.0415,
      "fill_rate_monotonicity": "increasing",
      "ending_backlog_monotonicity": "decreasing",
      "total_cost_monotonicity": "increasing",
      "max_fill_rate_drop": 0.262378,
      "max_backlog_increase": 4565.3632,
      "max_total_cost_increase": 0.0,
      "fill_rate_cross_service_threshold_at": 0.85,
      "fill_rate_cross_soft_threshold_at": 0.85,
      "ending_backlog_cross_threshold_at": 0.85,
      "total_cost_cross_threshold_at": null,
      "safe_band_low": 1.0,
      "safe_band_high": 1.0,
      "steepest_fill_segment": [
        0.95,
        1.0
      ],
      "fill_rate_min": 0.689162,
      "fill_rate_max": 0.95154,
      "ending_backlog_min": 843.2095,
      "ending_backlog_max": 5408.5727,
      "total_cost_min": 19252771.1199,
      "total_cost_max": 19256325.8659,
      "external_procured_qty_min": 0.0,
      "external_procured_qty_max": 0.0,
      "avg_inventory_min": 8252105.768,
      "avg_inventory_max": 8253511.0415
    },
    {
      "parameter_key": "supplier_lead_time_node::SDC-VD0914690A",
      "parameter_group": "supplier_lead_time_node",
      "parameter_label": "Lead time fournisseur SDC-VD0914690A",
      "realism_focus": "supplier_lead_time",
      "levels": [
        0.7,
        0.85,
        1.0,
        1.2,
        1.5
      ],
      "baseline_fill_rate": 0.95154,
      "baseline_backlog": 843.2095,
      "baseline_total_cost": 19256325.8659,
      "baseline_external_procured_qty": 0.0,
      "baseline_avg_inventory": 8253511.0415,
      "fill_rate_monotonicity": "non_monotonic",
      "ending_backlog_monotonicity": "non_monotonic",
      "total_cost_monotonicity": "non_monotonic",
      "max_fill_rate_drop": 0.1353660000000001,
      "max_backlog_increase": 2355.3691,
      "max_total_cost_increase": 4552.50700000301,
      "fill_rate_cross_service_threshold_at": 0.7,
      "fill_rate_cross_soft_threshold_at": 0.7,
      "ending_backlog_cross_threshold_at": 0.7,
      "total_cost_cross_threshold_at": null,
      "safe_band_low": 1.0,
      "safe_band_high": 1.5,
      "steepest_fill_segment": [
        0.7,
        0.85
      ],
      "fill_rate_min": 0.816174,
      "fill_rate_max": 0.988973,
      "ending_backlog_min": 191.875,
      "ending_backlog_max": 3198.5786,
      "total_cost_min": 19238494.8332,
      "total_cost_max": 19260878.3729,
      "external_procured_qty_min": 0.0,
      "external_procured_qty_max": 0.0,
      "avg_inventory_min": 8142250.2481,
      "avg_inventory_max": 8287855.1544
    },
    {
      "parameter_key": "capacity_node::M-1430",
      "parameter_group": "capacity_node",
      "parameter_label": "Capacite M-1430",
      "realism_focus": "operations_capacity",
      "levels": [
        0.7,
        0.85,
        1.0,
        1.15,
        1.3
      ],
      "baseline_fill_rate": 0.95154,
      "baseline_backlog": 843.2095,
      "baseline_total_cost": 19256325.8659,
      "baseline_external_procured_qty": 0.0,
      "baseline_avg_inventory": 8253511.0415,
      "fill_rate_monotonicity": "increasing",
      "ending_backlog_monotonicity": "decreasing",
      "total_cost_monotonicity": "increasing",
      "max_fill_rate_drop": 0.13366500000000003,
      "max_backlog_increase": 2325.7671,
      "max_total_cost_increase": 26706.30640000105,
      "fill_rate_cross_service_threshold_at": 0.7,
      "fill_rate_cross_soft_threshold_at": 0.7,
      "ending_backlog_cross_threshold_at": 0.7,
      "total_cost_cross_threshold_at": null,
      "safe_band_low": 1.0,
      "safe_band_high": 1.3,
      "steepest_fill_segment": [
        0.7,
        0.85
      ],
      "fill_rate_min": 0.817875,
      "fill_rate_max": 0.988973,
      "ending_backlog_min": 191.875,
      "ending_backlog_max": 3168.9766,
      "total_cost_min": 19216067.2808,
      "total_cost_max": 19283032.1723,
      "external_procured_qty_min": 0.0,
      "external_procured_qty_max": 0.0,
      "avg_inventory_min": 8106704.1578,
      "avg_inventory_max": 8431933.2494
    },
    {
      "parameter_key": "lead_time_scale",
      "parameter_group": "global",
      "parameter_label": "Lead time global",
      "realism_focus": "exogenous_network",
      "levels": [
        0.75,
        0.9,
        1.0,
        1.1,
        1.25,
        1.5
      ],
      "baseline_fill_rate": 0.95154,
      "baseline_backlog": 843.2095,
      "baseline_total_cost": 19256325.8659,
      "baseline_external_procured_qty": 0.0,
      "baseline_avg_inventory": 8253511.0415,
      "fill_rate_monotonicity": "non_monotonic",
      "ending_backlog_monotonicity": "non_monotonic",
      "total_cost_monotonicity": "increasing",
      "max_fill_rate_drop": 0.10572500000000007,
      "max_backlog_increase": 1839.6021,
      "max_total_cost_increase": 1842408.8949000016,
      "fill_rate_cross_service_threshold_at": 0.75,
      "fill_rate_cross_soft_threshold_at": 0.75,
      "ending_backlog_cross_threshold_at": 0.75,
      "total_cost_cross_threshold_at": null,
      "safe_band_low": 1.0,
      "safe_band_high": 1.5,
      "steepest_fill_segment": [
        0.75,
        0.9
      ],
      "fill_rate_min": 0.845815,
      "fill_rate_max": 0.983342,
      "ending_backlog_min": 289.8439,
      "ending_backlog_max": 2682.8116,
      "total_cost_min": 14538454.5705,
      "total_cost_max": 21098734.7608,
      "external_procured_qty_min": 0.0,
      "external_procured_qty_max": 0.0,
      "avg_inventory_min": 6185644.8784,
      "avg_inventory_max": 9064632.423
    },
    {
      "parameter_key": "demand_item::item:268967",
      "parameter_group": "demand_item",
      "parameter_label": "Demande 268967",
      "realism_focus": "market_demand",
      "levels": [
        0.8,
        0.9,
        1.0,
        1.1,
        1.2
      ],
      "baseline_fill_rate": 0.95154,
      "baseline_backlog": 843.2095,
      "baseline_total_cost": 19256325.8659,
      "baseline_external_procured_qty": 0.0,
      "baseline_avg_inventory": 8253511.0415,
      "fill_rate_monotonicity": "decreasing",
      "ending_backlog_monotonicity": "increasing",
      "total_cost_monotonicity": "non_monotonic",
      "max_fill_rate_drop": 0.08262600000000009,
      "max_backlog_increase": 1665.7671,
      "max_total_cost_increase": 0.0,
      "fill_rate_cross_service_threshold_at": 1.1,
      "fill_rate_cross_soft_threshold_at": 1.1,
      "ending_backlog_cross_threshold_at": 1.1,
      "total_cost_cross_threshold_at": null,
      "safe_band_low": 0.8,
      "safe_band_high": 1.0,
      "steepest_fill_segment": [
        1.0,
        1.1
      ],
      "fill_rate_min": 0.868914,
      "fill_rate_max": 0.985333,
      "ending_backlog_min": 229.6875,
      "ending_backlog_max": 2508.9766,
      "total_cost_min": 19247909.938,
      "total_cost_max": 19256325.8659,
      "external_procured_qty_min": 0.0,
      "external_procured_qty_max": 0.0,
      "avg_inventory_min": 8214739.0653,
      "avg_inventory_max": 8307040.2724
    },
    {
      "parameter_key": "supplier_stock_node::SDC-VD0914690A",
      "parameter_group": "supplier_stock_node",
      "parameter_label": "Stock fournisseur SDC-VD0914690A",
      "realism_focus": "supplier_buffer",
      "levels": [
        0.6,
        0.8,
        1.0,
        1.2,
        1.4
      ],
      "baseline_fill_rate": 0.95154,
      "baseline_backlog": 843.2095,
      "baseline_total_cost": 19256325.8659,
      "baseline_external_procured_qty": 0.0,
      "baseline_avg_inventory": 8253511.0415,
      "fill_rate_monotonicity": "non_monotonic",
      "ending_backlog_monotonicity": "non_monotonic",
      "total_cost_monotonicity": "increasing",
      "max_fill_rate_drop": 0.0005490000000000217,
      "max_backlog_increase": 9.545599999999922,
      "max_total_cost_increase": 813.276399999857,
      "fill_rate_cross_service_threshold_at": null,
      "fill_rate_cross_soft_threshold_at": null,
      "ending_backlog_cross_threshold_at": null,
      "total_cost_cross_threshold_at": null,
      "safe_band_low": 0.6,
      "safe_band_high": 1.4,
      "steepest_fill_segment": [
        1.2,
        1.4
      ],
      "fill_rate_min": 0.950991,
      "fill_rate_max": 0.956732,
      "ending_backlog_min": 752.8684,
      "ending_backlog_max": 852.7551,
      "total_cost_min": 19255611.4505,
      "total_cost_max": 19257139.1423,
      "external_procured_qty_min": 0.0,
      "external_procured_qty_max": 0.0,
      "avg_inventory_min": 8253021.28,
      "avg_inventory_max": 8254000.2066
    },
    {
      "parameter_key": "supplier_reliability_node::SDC-VD0914690A",
      "parameter_group": "supplier_reliability_node",
      "parameter_label": "Fiabilite fournisseur SDC-VD0914690A",
      "realism_focus": "supplier_reliability",
      "levels": [
        0.85,
        0.9,
        0.95,
        1.0
      ],
      "baseline_fill_rate": 0.95154,
      "baseline_backlog": 843.2095,
      "baseline_total_cost": 19256325.8659,
      "baseline_external_procured_qty": 0.0,
      "baseline_avg_inventory": 8253511.0415,
      "fill_rate_monotonicity": "increasing",
      "ending_backlog_monotonicity": "decreasing",
      "total_cost_monotonicity": "increasing",
      "max_fill_rate_drop": 0.00041200000000007897,
      "max_backlog_increase": 7.159199999999942,
      "max_total_cost_increase": 0.0,
      "fill_rate_cross_service_threshold_at": null,
      "fill_rate_cross_soft_threshold_at": null,
      "ending_backlog_cross_threshold_at": null,
      "total_cost_cross_threshold_at": null,
      "safe_band_low": 0.85,
      "safe_band_high": 1.0,
      "steepest_fill_segment": [
        0.9,
        0.95
      ],
      "fill_rate_min": 0.951128,
      "fill_rate_max": 0.95154,
      "ending_backlog_min": 843.2095,
      "ending_backlog_max": 850.3687,
      "total_cost_min": 19256039.4597,
      "total_cost_max": 19256325.8659,
      "external_procured_qty_min": 0.0,
      "external_procured_qty_max": 0.0,
      "avg_inventory_min": 8253327.4775,
      "avg_inventory_max": 8253511.0415
    },
    {
      "parameter_key": "demand_item::item:268091",
      "parameter_group": "demand_item",
      "parameter_label": "Demande 268091",
      "realism_focus": "market_demand",
      "levels": [
        0.8,
        0.9,
        1.0,
        1.1,
        1.2
      ],
      "baseline_fill_rate": 0.95154,
      "baseline_backlog": 843.2095,
      "baseline_total_cost": 19256325.8659,
      "baseline_external_procured_qty": 0.0,
      "baseline_avg_inventory": 8253511.0415,
      "fill_rate_monotonicity": "non_monotonic",
      "ending_backlog_monotonicity": "non_monotonic",
      "total_cost_monotonicity": "increasing",
      "max_fill_rate_drop": 0.0003290000000000237,
      "max_backlog_increase": 0.0,
      "max_total_cost_increase": 1675.723100002855,
      "fill_rate_cross_service_threshold_at": null,
      "fill_rate_cross_soft_threshold_at": null,
      "ending_backlog_cross_threshold_at": null,
      "total_cost_cross_threshold_at": null,
      "safe_band_low": 0.8,
      "safe_band_high": 1.2,
      "steepest_fill_segment": [
        1.0,
        1.1
      ],
      "fill_rate_min": 0.951211,
      "fill_rate_max": 0.958325,
      "ending_backlog_min": 759.6798,
      "ending_backlog_max": 843.2095,
      "total_cost_min": 19254636.7265,
      "total_cost_max": 19258001.589,
      "external_procured_qty_min": 0.0,
      "external_procured_qty_max": 0.0,
      "avg_inventory_min": 8251275.3215,
      "avg_inventory_max": 8255675.2064
    }
  ],
  "strongest_cost_effects": [
    {
      "parameter_key": "holding_cost_scale",
      "parameter_group": "global",
      "parameter_label": "Cout de stock",
      "realism_focus": "economic_penalty",
      "levels": [
        0.5,
        0.75,
        1.0,
        1.25,
        1.5
      ],
      "baseline_fill_rate": 0.95154,
      "baseline_backlog": 843.2095,
      "baseline_total_cost": 19256325.8659,
      "baseline_external_procured_qty": 0.0,
      "baseline_avg_inventory": 8253511.0415,
      "fill_rate_monotonicity": "flat",
      "ending_backlog_monotonicity": "flat",
      "total_cost_monotonicity": "increasing",
      "max_fill_rate_drop": 0.0,
      "max_backlog_increase": 0.0,
      "max_total_cost_increase": 9585440.158300001,
      "fill_rate_cross_service_threshold_at": null,
      "fill_rate_cross_soft_threshold_at": null,
      "ending_backlog_cross_threshold_at": null,
      "total_cost_cross_threshold_at": 1.25,
      "safe_band_low": 0.5,
      "safe_band_high": 1.0,
      "steepest_fill_segment": [
        0.5,
        0.75
      ],
      "fill_rate_min": 0.95154,
      "fill_rate_max": 0.95154,
      "ending_backlog_min": 843.2095,
      "ending_backlog_max": 843.2095,
      "total_cost_min": 9670885.7076,
      "total_cost_max": 28841766.0242,
      "external_procured_qty_min": 0.0,
      "external_procured_qty_max": 0.0,
      "avg_inventory_min": 8253511.0415,
      "avg_inventory_max": 8253511.0415
    },
    {
      "parameter_key": "lead_time_scale",
      "parameter_group": "global",
      "parameter_label": "Lead time global",
      "realism_focus": "exogenous_network",
      "levels": [
        0.75,
        0.9,
        1.0,
        1.1,
        1.25,
        1.5
      ],
      "baseline_fill_rate": 0.95154,
      "baseline_backlog": 843.2095,
      "baseline_total_cost": 19256325.8659,
      "baseline_external_procured_qty": 0.0,
      "baseline_avg_inventory": 8253511.0415,
      "fill_rate_monotonicity": "non_monotonic",
      "ending_backlog_monotonicity": "non_monotonic",
      "total_cost_monotonicity": "increasing",
      "max_fill_rate_drop": 0.10572500000000007,
      "max_backlog_increase": 1839.6021,
      "max_total_cost_increase": 1842408.8949000016,
      "fill_rate_cross_service_threshold_at": 0.75,
      "fill_rate_cross_soft_threshold_at": 0.75,
      "ending_backlog_cross_threshold_at": 0.75,
      "total_cost_cross_threshold_at": null,
      "safe_band_low": 1.0,
      "safe_band_high": 1.5,
      "steepest_fill_segment": [
        0.75,
        0.9
      ],
      "fill_rate_min": 0.845815,
      "fill_rate_max": 0.983342,
      "ending_backlog_min": 289.8439,
      "ending_backlog_max": 2682.8116,
      "total_cost_min": 14538454.5705,
      "total_cost_max": 21098734.7608,
      "external_procured_qty_min": 0.0,
      "external_procured_qty_max": 0.0,
      "avg_inventory_min": 6185644.8784,
      "avg_inventory_max": 9064632.423
    },
    {
      "parameter_key": "review_period_scale",
      "parameter_group": "global",
      "parameter_label": "Periode de revue",
      "realism_focus": "planning_policy",
      "levels": [
        1.0,
        2.0,
        3.0,
        5.0,
        7.0
      ],
      "baseline_fill_rate": 0.95154,
      "baseline_backlog": 843.2095,
      "baseline_total_cost": 19256325.8659,
      "baseline_external_procured_qty": 0.0,
      "baseline_avg_inventory": 8253511.0415,
      "fill_rate_monotonicity": "decreasing",
      "ending_backlog_monotonicity": "increasing",
      "total_cost_monotonicity": "increasing",
      "max_fill_rate_drop": 0.46760700000000005,
      "max_backlog_increase": 8136.3581,
      "max_total_cost_increase": 506206.39169999957,
      "fill_rate_cross_service_threshold_at": 2.0,
      "fill_rate_cross_soft_threshold_at": 2.0,
      "ending_backlog_cross_threshold_at": 2.0,
      "total_cost_cross_threshold_at": null,
      "safe_band_low": 1.0,
      "safe_band_high": 1.0,
      "steepest_fill_segment": [
        2.0,
        3.0
      ],
      "fill_rate_min": 0.483933,
      "fill_rate_max": 0.95154,
      "ending_backlog_min": 843.2095,
      "ending_backlog_max": 8979.5676,
      "total_cost_min": 19256325.8659,
      "total_cost_max": 19762532.2576,
      "external_procured_qty_min": 0.0,
      "external_procured_qty_max": 0.0,
      "avg_inventory_min": 8253511.0415,
      "avg_inventory_max": 8708616.9734
    },
    {
      "parameter_key": "capacity_node::M-1430",
      "parameter_group": "capacity_node",
      "parameter_label": "Capacite M-1430",
      "realism_focus": "operations_capacity",
      "levels": [
        0.7,
        0.85,
        1.0,
        1.15,
        1.3
      ],
      "baseline_fill_rate": 0.95154,
      "baseline_backlog": 843.2095,
      "baseline_total_cost": 19256325.8659,
      "baseline_external_procured_qty": 0.0,
      "baseline_avg_inventory": 8253511.0415,
      "fill_rate_monotonicity": "increasing",
      "ending_backlog_monotonicity": "decreasing",
      "total_cost_monotonicity": "increasing",
      "max_fill_rate_drop": 0.13366500000000003,
      "max_backlog_increase": 2325.7671,
      "max_total_cost_increase": 26706.30640000105,
      "fill_rate_cross_service_threshold_at": 0.7,
      "fill_rate_cross_soft_threshold_at": 0.7,
      "ending_backlog_cross_threshold_at": 0.7,
      "total_cost_cross_threshold_at": null,
      "safe_band_low": 1.0,
      "safe_band_high": 1.3,
      "steepest_fill_segment": [
        0.7,
        0.85
      ],
      "fill_rate_min": 0.817875,
      "fill_rate_max": 0.988973,
      "ending_backlog_min": 191.875,
      "ending_backlog_max": 3168.9766,
      "total_cost_min": 19216067.2808,
      "total_cost_max": 19283032.1723,
      "external_procured_qty_min": 0.0,
      "external_procured_qty_max": 0.0,
      "avg_inventory_min": 8106704.1578,
      "avg_inventory_max": 8431933.2494
    },
    {
      "parameter_key": "supplier_lead_time_node::SDC-1450",
      "parameter_group": "supplier_lead_time_node",
      "parameter_label": "Lead time fournisseur SDC-1450",
      "realism_focus": "supplier_lead_time",
      "levels": [
        0.7,
        0.85,
        1.0,
        1.2,
        1.5
      ],
      "baseline_fill_rate": 0.95154,
      "baseline_backlog": 843.2095,
      "baseline_total_cost": 19256325.8659,
      "baseline_external_procured_qty": 0.0,
      "baseline_avg_inventory": 8253511.0415,
      "fill_rate_monotonicity": "flat",
      "ending_backlog_monotonicity": "flat",
      "total_cost_monotonicity": "increasing",
      "max_fill_rate_drop": 0.0,
      "max_backlog_increase": 0.0,
      "max_total_cost_increase": 16502.672000002116,
      "fill_rate_cross_service_threshold_at": null,
      "fill_rate_cross_soft_threshold_at": null,
      "ending_backlog_cross_threshold_at": null,
      "total_cost_cross_threshold_at": null,
      "safe_band_low": 0.7,
      "safe_band_high": 1.5,
      "steepest_fill_segment": [
        0.7,
        0.85
      ],
      "fill_rate_min": 0.95154,
      "fill_rate_max": 0.95154,
      "ending_backlog_min": 843.2095,
      "ending_backlog_max": 843.2095,
      "total_cost_min": 19234382.6555,
      "total_cost_max": 19272828.5379,
      "external_procured_qty_min": 0.0,
      "external_procured_qty_max": 0.0,
      "avg_inventory_min": 8227995.6806,
      "avg_inventory_max": 8272700.195
    },
    {
      "parameter_key": "supplier_stock_scale",
      "parameter_group": "global",
      "parameter_label": "Stock fournisseur global",
      "realism_focus": "buffer_policy",
      "levels": [
        0.5,
        0.75,
        1.0,
        1.25,
        1.5
      ],
      "baseline_fill_rate": 0.95154,
      "baseline_backlog": 843.2095,
      "baseline_total_cost": 19256325.8659,
      "baseline_external_procured_qty": 0.0,
      "baseline_avg_inventory": 8253511.0415,
      "fill_rate_monotonicity": "non_monotonic",
      "ending_backlog_monotonicity": "non_monotonic",
      "total_cost_monotonicity": "increasing",
      "max_fill_rate_drop": 0.0,
      "max_backlog_increase": 0.0,
      "max_total_cost_increase": 8722.381000000983,
      "fill_rate_cross_service_threshold_at": null,
      "fill_rate_cross_soft_threshold_at": null,
      "ending_backlog_cross_threshold_at": null,
      "total_cost_cross_threshold_at": null,
      "safe_band_low": 0.5,
      "safe_band_high": 1.5,
      "steepest_fill_segment": [
        1.0,
        1.25
      ],
      "fill_rate_min": 0.95154,
      "fill_rate_max": 0.95632,
      "ending_backlog_min": 760.0276,
      "ending_backlog_max": 843.2095,
      "total_cost_min": 19247485.2996,
      "total_cost_max": 19265048.2469,
      "external_procured_qty_min": 0.0,
      "external_procured_qty_max": 0.0,
      "avg_inventory_min": 8248242.667,
      "avg_inventory_max": 8258833.5399
    },
    {
      "parameter_key": "supplier_lead_time_node::SDC-VD0914690A",
      "parameter_group": "supplier_lead_time_node",
      "parameter_label": "Lead time fournisseur SDC-VD0914690A",
      "realism_focus": "supplier_lead_time",
      "levels": [
        0.7,
        0.85,
        1.0,
        1.2,
        1.5
      ],
      "baseline_fill_rate": 0.95154,
      "baseline_backlog": 843.2095,
      "baseline_total_cost": 19256325.8659,
      "baseline_external_procured_qty": 0.0,
      "baseline_avg_inventory": 8253511.0415,
      "fill_rate_monotonicity": "non_monotonic",
      "ending_backlog_monotonicity": "non_monotonic",
      "total_cost_monotonicity": "non_monotonic",
      "max_fill_rate_drop": 0.1353660000000001,
      "max_backlog_increase": 2355.3691,
      "max_total_cost_increase": 4552.50700000301,
      "fill_rate_cross_service_threshold_at": 0.7,
      "fill_rate_cross_soft_threshold_at": 0.7,
      "ending_backlog_cross_threshold_at": 0.7,
      "total_cost_cross_threshold_at": null,
      "safe_band_low": 1.0,
      "safe_band_high": 1.5,
      "steepest_fill_segment": [
        0.7,
        0.85
      ],
      "fill_rate_min": 0.816174,
      "fill_rate_max": 0.988973,
      "ending_backlog_min": 191.875,
      "ending_backlog_max": 3198.5786,
      "total_cost_min": 19238494.8332,
      "total_cost_max": 19260878.3729,
      "external_procured_qty_min": 0.0,
      "external_procured_qty_max": 0.0,
      "avg_inventory_min": 8142250.2481,
      "avg_inventory_max": 8287855.1544
    },
    {
      "parameter_key": "capacity_node::M-1810",
      "parameter_group": "capacity_node",
      "parameter_label": "Capacite M-1810",
      "realism_focus": "operations_capacity",
      "levels": [
        0.7,
        0.85,
        1.0,
        1.15,
        1.3
      ],
      "baseline_fill_rate": 0.95154,
      "baseline_backlog": 843.2095,
      "baseline_total_cost": 19256325.8659,
      "baseline_external_procured_qty": 0.0,
      "baseline_avg_inventory": 8253511.0415,
      "fill_rate_monotonicity": "flat",
      "ending_backlog_monotonicity": "flat",
      "total_cost_monotonicity": "increasing",
      "max_fill_rate_drop": 0.0,
      "max_backlog_increase": 0.0,
      "max_total_cost_increase": 4471.096900001168,
      "fill_rate_cross_service_threshold_at": null,
      "fill_rate_cross_soft_threshold_at": null,
      "ending_backlog_cross_threshold_at": null,
      "total_cost_cross_threshold_at": null,
      "safe_band_low": 0.7,
      "safe_band_high": 1.3,
      "steepest_fill_segment": [
        0.7,
        0.85
      ],
      "fill_rate_min": 0.95154,
      "fill_rate_max": 0.95154,
      "ending_backlog_min": 843.2095,
      "ending_backlog_max": 843.2095,
      "total_cost_min": 19251854.7689,
      "total_cost_max": 19260796.9628,
      "external_procured_qty_min": 0.0,
      "external_procured_qty_max": 0.0,
      "avg_inventory_min": 8236435.0012,
      "avg_inventory_max": 8270587.0818
    },
    {
      "parameter_key": "safety_stock_days_scale",
      "parameter_group": "global",
      "parameter_label": "Safety stock global",
      "realism_focus": "buffer_policy",
      "levels": [
        0.25,
        0.5,
        0.75,
        1.0,
        1.25,
        1.5,
        2.0
      ],
      "baseline_fill_rate": 0.95154,
      "baseline_backlog": 843.2095,
      "baseline_total_cost": 19256325.8659,
      "baseline_external_procured_qty": 0.0,
      "baseline_avg_inventory": 8253511.0415,
      "fill_rate_monotonicity": "flat",
      "ending_backlog_monotonicity": "flat",
      "total_cost_monotonicity": "increasing",
      "max_fill_rate_drop": 0.0,
      "max_backlog_increase": 0.0,
      "max_total_cost_increase": 3910.592000000179,
      "fill_rate_cross_service_threshold_at": null,
      "fill_rate_cross_soft_threshold_at": null,
      "ending_backlog_cross_threshold_at": null,
      "total_cost_cross_threshold_at": null,
      "safe_band_low": 0.25,
      "safe_band_high": 2.0,
      "steepest_fill_segment": [
        0.25,
        0.5
      ],
      "fill_rate_min": 0.95154,
      "fill_rate_max": 0.95154,
      "ending_backlog_min": 843.2095,
      "ending_backlog_max": 843.2095,
      "total_cost_min": 19254080.44,
      "total_cost_max": 19260236.4579,
      "external_procured_qty_min": 0.0,
      "external_procured_qty_max": 0.0,
      "avg_inventory_min": 8251245.0649,
      "avg_inventory_max": 8258058.2415
    },
    {
      "parameter_key": "supplier_reliability_node::SDC-1450",
      "parameter_group": "supplier_reliability_node",
      "parameter_label": "Fiabilite fournisseur SDC-1450",
      "realism_focus": "supplier_reliability",
      "levels": [
        0.85,
        0.9,
        0.95,
        1.0
      ],
      "baseline_fill_rate": 0.95154,
      "baseline_backlog": 843.2095,
      "baseline_total_cost": 19256325.8659,
      "baseline_external_procured_qty": 0.0,
      "baseline_avg_inventory": 8253511.0415,
      "fill_rate_monotonicity": "decreasing",
      "ending_backlog_monotonicity": "increasing",
      "total_cost_monotonicity": "decreasing",
      "max_fill_rate_drop": 0.0,
      "max_backlog_increase": 0.0,
      "max_total_cost_increase": 2084.5060000009835,
      "fill_rate_cross_service_threshold_at": null,
      "fill_rate_cross_soft_threshold_at": null,
      "ending_backlog_cross_threshold_at": null,
      "total_cost_cross_threshold_at": null,
      "safe_band_low": 0.85,
      "safe_band_high": 1.0,
      "steepest_fill_segment": [
        0.9,
        0.95
      ],
      "fill_rate_min": 0.95154,
      "fill_rate_max": 0.955806,
      "ending_backlog_min": 768.9766,
      "ending_backlog_max": 843.2095,
      "total_cost_min": 19256325.8659,
      "total_cost_max": 19258410.3719,
      "external_procured_qty_min": 0.0,
      "external_procured_qty_max": 0.0,
      "avg_inventory_min": 8253031.2912,
      "avg_inventory_max": 8253511.0415
    }
  ]
}