{
  "input_file": "etudecas/simulation/sensibility/result/cases/capacity_M-1810_high/input_case.json",
  "scenario_id": "scn:BASE",
  "sim_days": 30,
  "policy": {
    "safety_stock_days": 7.0,
    "review_period_days": 1,
    "fg_target_days": 0.0,
    "production_gap_gain": 0.25,
    "production_smoothing": 0.2,
    "stochastic_lead_times": true,
    "seed": 42,
    "economic_policy": {
      "transport_cost_floor_per_unit": 0.02,
      "transport_cost_per_km_per_unit": 8e-05,
      "purchase_cost_floor_per_unit": 0.01,
      "holding_cost_scale": 1.0,
      "external_procurement_enabled": true,
      "external_procurement_lead_days": 4,
      "external_procurement_daily_cap_days": 2.0,
      "external_procurement_min_daily_cap_qty": 0.0,
      "external_procurement_unit_cost": 0.0,
      "external_procurement_cost_multiplier": 2.0,
      "external_procurement_transport_cost_per_unit": 0.04
    }
  },
  "counts": {
    "nodes": 28,
    "edges": 34,
    "lanes": 34,
    "demand_rows": 2
  },
  "production_tracking": {
    "input_material_pairs": [
      {
        "node_id": "M-1430",
        "item_id": "item:038005"
      },
      {
        "node_id": "M-1430",
        "item_id": "item:042342"
      },
      {
        "node_id": "M-1430",
        "item_id": "item:333362"
      },
      {
        "node_id": "M-1430",
        "item_id": "item:344135"
      },
      {
        "node_id": "M-1430",
        "item_id": "item:708073"
      },
      {
        "node_id": "M-1430",
        "item_id": "item:730384"
      },
      {
        "node_id": "M-1430",
        "item_id": "item:734545"
      },
      {
        "node_id": "M-1430",
        "item_id": "item:773474"
      },
      {
        "node_id": "M-1810",
        "item_id": "item:001757"
      },
      {
        "node_id": "M-1810",
        "item_id": "item:001848"
      },
      {
        "node_id": "M-1810",
        "item_id": "item:001893"
      },
      {
        "node_id": "M-1810",
        "item_id": "item:002612"
      },
      {
        "node_id": "M-1810",
        "item_id": "item:016332"
      },
      {
        "node_id": "M-1810",
        "item_id": "item:029313"
      },
      {
        "node_id": "M-1810",
        "item_id": "item:039668"
      },
      {
        "node_id": "M-1810",
        "item_id": "item:049371"
      },
      {
        "node_id": "M-1810",
        "item_id": "item:055703"
      },
      {
        "node_id": "M-1810",
        "item_id": "item:099439"
      },
      {
        "node_id": "M-1810",
        "item_id": "item:338928"
      },
      {
        "node_id": "M-1810",
        "item_id": "item:338929"
      },
      {
        "node_id": "M-1810",
        "item_id": "item:426331"
      },
      {
        "node_id": "M-1810",
        "item_id": "item:693055"
      },
      {
        "node_id": "M-1810",
        "item_id": "item:693710"
      }
    ],
    "output_product_pairs": [
      {
        "node_id": "M-1430",
        "item_id": "item:268967"
      },
      {
        "node_id": "M-1810",
        "item_id": "item:268091"
      }
    ],
    "unconstrained_process_inputs_not_in_relations": [],
    "item_unit_map": {
      "item:001757": "KG",
      "item:001848": "KG",
      "item:001893": "KG",
      "item:002612": "KG",
      "item:016332": "KG",
      "item:029313": "KG",
      "item:038005": "KG",
      "item:039668": "KG",
      "item:042342": "UN",
      "item:049371": "KG",
      "item:055703": "KG",
      "item:099439": "KG",
      "item:268091": "UN",
      "item:268967": "UN",
      "item:333362": "UN",
      "item:338928": "UN",
      "item:338929": "UN",
      "item:344135": "UN",
      "item:426331": "UN",
      "item:693055": "G",
      "item:693710": "G",
      "item:708073": "KG",
      "item:730384": "M",
      "item:734545": "UN",
      "item:773474": "G"
    },
    "input_unit_conversions_applied": [
      {
        "node_id": "M-1430",
        "item_id": "item:038005",
        "from_unit": "G",
        "to_unit": "KG"
      },
      {
        "node_id": "M-1430",
        "item_id": "item:708073",
        "from_unit": "G",
        "to_unit": "KG"
      },
      {
        "node_id": "M-1810",
        "item_id": "item:001757",
        "from_unit": "G",
        "to_unit": "KG"
      },
      {
        "node_id": "M-1810",
        "item_id": "item:001848",
        "from_unit": "G",
        "to_unit": "KG"
      },
      {
        "node_id": "M-1810",
        "item_id": "item:016332",
        "from_unit": "G",
        "to_unit": "KG"
      },
      {
        "node_id": "M-1810",
        "item_id": "item:029313",
        "from_unit": "G",
        "to_unit": "KG"
      },
      {
        "node_id": "M-1810",
        "item_id": "item:039668",
        "from_unit": "G",
        "to_unit": "KG"
      },
      {
        "node_id": "M-1810",
        "item_id": "item:049371",
        "from_unit": "G",
        "to_unit": "KG"
      },
      {
        "node_id": "M-1810",
        "item_id": "item:055703",
        "from_unit": "G",
        "to_unit": "KG"
      },
      {
        "node_id": "M-1810",
        "item_id": "item:099439",
        "from_unit": "G",
        "to_unit": "KG"
      }
    ],
    "input_unit_mismatch_not_converted": [],
    "customer_demand_daily_signal": [
      {
        "node_id": "C-XXXXX",
        "item_id": "item:268091",
        "demand_per_day": 24.0
      },
      {
        "node_id": "C-XXXXX",
        "item_id": "item:268967",
        "demand_per_day": 20.0
      }
    ],
    "propagated_demand_daily_signal": [
      {
        "node_id": "C-XXXXX",
        "item_id": "item:268091",
        "demand_per_day": 24.0
      },
      {
        "node_id": "C-XXXXX",
        "item_id": "item:268967",
        "demand_per_day": 20.0
      },
      {
        "node_id": "DC-1920",
        "item_id": "item:268091",
        "demand_per_day": 24.0
      },
      {
        "node_id": "DC-1920",
        "item_id": "item:268967",
        "demand_per_day": 20.0
      },
      {
        "node_id": "M-1430",
        "item_id": "item:268967",
        "demand_per_day": 20.0
      },
      {
        "node_id": "M-1810",
        "item_id": "item:268091",
        "demand_per_day": 24.0
      }
    ],
    "assumed_supplier_nodes": [
      "SDC-1450"
    ],
    "assumed_supply_edges": [
      "edge:SDC-1450_TO_M-1810_693710_Q"
    ],
    "externally_sourced_unmodeled_pairs": [
      {
        "node_id": "SDC-1450",
        "item_id": "item:693055"
      },
      {
        "node_id": "SDC-1450",
        "item_id": "item:693710"
      },
      {
        "node_id": "SDC-1450",
        "item_id": "item:773474"
      },
      {
        "node_id": "SDC-VD0500655A",
        "item_id": "item:002612"
      },
      {
        "node_id": "SDC-VD0505677A",
        "item_id": "item:099439"
      },
      {
        "node_id": "SDC-VD0508918A",
        "item_id": "item:730384"
      },
      {
        "node_id": "SDC-VD0514881A",
        "item_id": "item:016332"
      },
      {
        "node_id": "SDC-VD0518684A",
        "item_id": "item:001893"
      },
      {
        "node_id": "SDC-VD0519670A",
        "item_id": "item:001848"
      },
      {
        "node_id": "SDC-VD0519670A",
        "item_id": "item:029313"
      },
      {
        "node_id": "SDC-VD0520115A",
        "item_id": "item:708073"
      },
      {
        "node_id": "SDC-VD0520132A",
        "item_id": "item:038005"
      },
      {
        "node_id": "SDC-VD0520132A",
        "item_id": "item:049371"
      },
      {
        "node_id": "SDC-VD0525412A",
        "item_id": "item:333362"
      },
      {
        "node_id": "SDC-VD0901566A",
        "item_id": "item:338928"
      },
      {
        "node_id": "SDC-VD0910216A",
        "item_id": "item:001893"
      },
      {
        "node_id": "SDC-VD0910216A",
        "item_id": "item:002612"
      },
      {
        "node_id": "SDC-VD0914320A",
        "item_id": "item:055703"
      },
      {
        "node_id": "SDC-VD0914360C",
        "item_id": "item:338929"
      },
      {
        "node_id": "SDC-VD0914690A",
        "item_id": "item:042342"
      },
      {
        "node_id": "SDC-VD0951020A",
        "item_id": "item:001757"
      },
      {
        "node_id": "SDC-VD0951020A",
        "item_id": "item:001848"
      },
      {
        "node_id": "SDC-VD0964290A",
        "item_id": "item:055703"
      },
      {
        "node_id": "SDC-VD0989480A",
        "item_id": "item:426331"
      },
      {
        "node_id": "SDC-VD0990780A",
        "item_id": "item:002612"
      },
      {
        "node_id": "SDC-VD0993480A",
        "item_id": "item:344135"
      },
      {
        "node_id": "SDC-VD1091642A",
        "item_id": "item:001893"
      },
      {
        "node_id": "SDC-VD1091642A",
        "item_id": "item:002612"
      },
      {
        "node_id": "SDC-VD1095770A",
        "item_id": "item:734545"
      },
      {
        "node_id": "SDC-VD1096202A",
        "item_id": "item:039668"
      }
    ],
    "opening_stock_bootstrap_pairs": [
      {
        "node_id": "M-1430",
        "item_id": "item:038005",
        "lead_days": 8,
        "cover_days": 16,
        "daily_req_at_cap": 0.437479,
        "added_opening_qty": 6.99967,
        "target_opening_stock": 6.99967
      },
      {
        "node_id": "M-1430",
        "item_id": "item:042342",
        "lead_days": 8,
        "cover_days": 16,
        "daily_req_at_cap": 1508.55,
        "added_opening_qty": 24136.8,
        "target_opening_stock": 24136.8
      },
      {
        "node_id": "M-1430",
        "item_id": "item:333362",
        "lead_days": 8,
        "cover_days": 16,
        "daily_req_at_cap": 25.0,
        "added_opening_qty": 400.0,
        "target_opening_stock": 400.0
      },
      {
        "node_id": "M-1430",
        "item_id": "item:344135",
        "lead_days": 8,
        "cover_days": 16,
        "daily_req_at_cap": 25.0,
        "added_opening_qty": 400.0,
        "target_opening_stock": 400.0
      },
      {
        "node_id": "M-1430",
        "item_id": "item:708073",
        "lead_days": 8,
        "cover_days": 16,
        "daily_req_at_cap": 0.19825,
        "added_opening_qty": 3.172,
        "target_opening_stock": 3.172
      },
      {
        "node_id": "M-1430",
        "item_id": "item:730384",
        "lead_days": 8,
        "cover_days": 16,
        "daily_req_at_cap": 5.3,
        "added_opening_qty": 84.8,
        "target_opening_stock": 84.8
      },
      {
        "node_id": "M-1430",
        "item_id": "item:734545",
        "lead_days": 8,
        "cover_days": 16,
        "daily_req_at_cap": 0.2,
        "added_opening_qty": 3.2,
        "target_opening_stock": 3.2
      },
      {
        "node_id": "M-1430",
        "item_id": "item:773474",
        "lead_days": 8,
        "cover_days": 16,
        "daily_req_at_cap": 241.36795,
        "added_opening_qty": 3861.8872,
        "target_opening_stock": 3861.8872
      },
      {
        "node_id": "M-1810",
        "item_id": "item:001757",
        "lead_days": 8,
        "cover_days": 16,
        "daily_req_at_cap": 0.04872,
        "added_opening_qty": 0.77952,
        "target_opening_stock": 0.77952
      },
      {
        "node_id": "M-1810",
        "item_id": "item:001848",
        "lead_days": 8,
        "cover_days": 16,
        "daily_req_at_cap": 0.03654,
        "added_opening_qty": 0.58464,
        "target_opening_stock": 0.58464
      },
      {
        "node_id": "M-1810",
        "item_id": "item:001893",
        "lead_days": 8,
        "cover_days": 16,
        "daily_req_at_cap": 0.23142,
        "added_opening_qty": 3.70272,
        "target_opening_stock": 3.70272
      },
      {
        "node_id": "M-1810",
        "item_id": "item:002612",
        "lead_days": 8,
        "cover_days": 16,
        "daily_req_at_cap": 0.0609,
        "added_opening_qty": 0.9744,
        "target_opening_stock": 0.9744
      },
      {
        "node_id": "M-1810",
        "item_id": "item:016332",
        "lead_days": 8,
        "cover_days": 16,
        "daily_req_at_cap": 0.014616,
        "added_opening_qty": 0.233856,
        "target_opening_stock": 0.233856
      },
      {
        "node_id": "M-1810",
        "item_id": "item:029313",
        "lead_days": 8,
        "cover_days": 16,
        "daily_req_at_cap": 0.001218,
        "added_opening_qty": 0.019488,
        "target_opening_stock": 0.019488
      },
      {
        "node_id": "M-1810",
        "item_id": "item:039668",
        "lead_days": 8,
        "cover_days": 16,
        "daily_req_at_cap": 0.001218,
        "added_opening_qty": 0.019488,
        "target_opening_stock": 0.019488
      },
      {
        "node_id": "M-1810",
        "item_id": "item:049371",
        "lead_days": 8,
        "cover_days": 16,
        "daily_req_at_cap": 0.045066,
        "added_opening_qty": 0.721056,
        "target_opening_stock": 0.721056
      },
      {
        "node_id": "M-1810",
        "item_id": "item:055703",
        "lead_days": 8,
        "cover_days": 16,
        "daily_req_at_cap": 0.002436,
        "added_opening_qty": 0.038976,
        "target_opening_stock": 0.038976
      },
      {
        "node_id": "M-1810",
        "item_id": "item:099439",
        "lead_days": 8,
        "cover_days": 16,
        "daily_req_at_cap": 0.0609,
        "added_opening_qty": 0.9744,
        "target_opening_stock": 0.9744
      },
      {
        "node_id": "M-1810",
        "item_id": "item:338928",
        "lead_days": 8,
        "cover_days": 16,
        "daily_req_at_cap": 30.0,
        "added_opening_qty": 480.0,
        "target_opening_stock": 480.0
      },
      {
        "node_id": "M-1810",
        "item_id": "item:338929",
        "lead_days": 8,
        "cover_days": 16,
        "daily_req_at_cap": 30.0,
        "added_opening_qty": 480.0,
        "target_opening_stock": 480.0
      },
      {
        "node_id": "M-1810",
        "item_id": "item:426331",
        "lead_days": 8,
        "cover_days": 16,
        "daily_req_at_cap": 0.33,
        "added_opening_qty": 5.28,
        "target_opening_stock": 5.28
      },
      {
        "node_id": "M-1810",
        "item_id": "item:693055",
        "lead_days": 8,
        "cover_days": 16,
        "daily_req_at_cap": 12.18,
        "added_opening_qty": 194.88,
        "target_opening_stock": 194.88
      }
    ],
    "lane_purchase_cost_stats": {
      "lanes_with_positive_purchase_cost": 34,
      "lanes_with_zero_purchase_cost": 0,
      "lanes_with_explicit_transport_cost": 1,
      "lanes_with_fallback_transport_cost": 33
    }
  },
  "kpis": {
    "total_demand": 1500.0,
    "total_served": 1465.4551,
    "ending_backlog": 34.5449,
    "fill_rate": 0.97697,
    "total_shipped": 55732.2743,
    "total_arrived": 35325.1366,
    "total_produced": 1461.9554,
    "avg_inventory": 22992.2722,
    "ending_inventory": 12532.5396,
    "total_transport_cost": 3966.1173,
    "total_holding_cost": 22198.9558,
    "total_purchase_cost": 3057.393,
    "total_logistics_cost": 26165.0731,
    "total_cost": 29222.4661,
    "total_external_procured_ordered_qty": 53441.9471,
    "total_external_procured_arrived_qty": 49285.5578,
    "total_external_procured_rejected_qty": 19871.1759,
    "total_external_procured_qty": 53441.9471,
    "total_external_procurement_cost": 4036.2833,
    "total_opening_stock_bootstrap_qty": 30065.0674,
    "total_unreliable_loss_qty": 0.0,
    "cost_share_holding": 0.759654,
    "cost_share_transport": 0.135722,
    "cost_share_purchase": 0.104625
  },
  "economic_consistency": {
    "status": "ok",
    "warnings": [],
    "transport_cost_share_target_min": 0.02,
    "holding_cost_share_target_max": 0.9
  },
  "top_backlog_pairs": [
    {
      "node_id": "C-XXXXX",
      "item_id": "item:268967",
      "backlog": 28.96
    },
    {
      "node_id": "C-XXXXX",
      "item_id": "item:268091",
      "backlog": 5.5849
    }
  ]
}